flowdoc/__init__.py
flowdoc/cli.py
flowdoc/decorators.py
flowdoc/generator.py
flowdoc/models.py
flowdoc/parser.py
flowdoc/validator.py
flowdoc-0.0.0rc1.dist-info/METADATA
flowdoc-0.0.0rc1.dist-info/WHEEL
flowdoc-0.0.0rc1.dist-info/entry_points.txt
flowdoc-0.0.0rc1.dist-info/licenses/LICENSE
flowdoc-0.0.0rc1.dist-info/RECORD
