Metadata-Version: 2.4
Name: flowdoc
Version: 0.0.0rc1
Summary: Generate business flow diagrams from Python code decorators
Project-URL: Repository, https://github.com/jharibo/flowdoc
Project-URL: Homepage, https://github.com/jharibo/flowdoc
Project-URL: Issues, https://github.com/jharibo/flowdoc/issues
Project-URL: Documentation, https://github.com/jharibo/flowdoc#readme
Author-email: James Harrison <40500443+jharibo@users.noreply.github.com>
License: MIT
License-File: LICENSE
Keywords: business-process,diagram,documentation,flowchart,visualization
Classifier: Development Status :: 3 - Alpha
Classifier: Intended Audience :: Developers
Classifier: License :: OSI Approved :: MIT License
Classifier: Programming Language :: Python :: 3
Classifier: Programming Language :: Python :: 3.10
Classifier: Programming Language :: Python :: 3.11
Classifier: Programming Language :: Python :: 3.12
Classifier: Programming Language :: Python :: 3.13
Classifier: Programming Language :: Python :: 3.14
Classifier: Topic :: Software Development :: Documentation
Classifier: Topic :: Software Development :: Libraries :: Python Modules
Requires-Python: <3.15,>=3.10
Requires-Dist: click>=8.0
Requires-Dist: graphviz>=0.20
